[ 
  {"viewvalue": "Afghanistan", "value": "AF"}, 
  {"viewvalue": "Åland Islands", "value": "AX"}, 
  {"viewvalue": "Albania", "value": "AL"}, 
  {"viewvalue": "Algeria", "value": "DZ"}, 
  {"viewvalue": "American Samoa", "value": "AS"}, 
  {"viewvalue": "Andorra", "value": "AD"}, 
  {"viewvalue": "Angola", "value": "AO"}, 
  {"viewvalue": "Anguilla", "value": "AI"}, 
  {"viewvalue": "Antarctica", "value": "AQ"}, 
  {"viewvalue": "Antigua and Barbuda", "value": "AG"}, 
  {"viewvalue": "Argentina", "value": "AR"}, 
  {"viewvalue": "Armenia", "value": "AM"}, 
  {"viewvalue": "Aruba", "value": "AW"}, 
  {"viewvalue": "Australia", "value": "AU"}, 
  {"viewvalue": "Austria", "value": "AT"}, 
  {"viewvalue": "Azerbaijan", "value": "AZ"}, 
  {"viewvalue": "Bahamas", "value": "BS"}, 
  {"viewvalue": "Bahrain", "value": "BH"}, 
  {"viewvalue": "Bangladesh", "value": "BD"}, 
  {"viewvalue": "Barbados", "value": "BB"}, 
  {"viewvalue": "Belarus", "value": "BY"}, 
  {"viewvalue": "Belgium", "value": "BE"}, 
  {"viewvalue": "Belize", "value": "BZ"}, 
  {"viewvalue": "Benin", "value": "BJ"}, 
  {"viewvalue": "Bermuda", "value": "BM"}, 
  {"viewvalue": "Bhutan", "value": "BT"}, 
  {"viewvalue": "Bolivia", "value": "BO"}, 
  {"viewvalue": "Bosnia and Herzegovina", "value": "BA"}, 
  {"viewvalue": "Botswana", "value": "BW"}, 
  {"viewvalue": "Bouvet Island", "value": "BV"}, 
  {"viewvalue": "Brazil", "value": "BR"}, 
  {"viewvalue": "British Indian Ocean Territory", "value": "IO"}, 
  {"viewvalue": "Brunei Darussalam", "value": "BN"}, 
  {"viewvalue": "Bulgaria", "value": "BG"}, 
  {"viewvalue": "Burkina Faso", "value": "BF"}, 
  {"viewvalue": "Burundi", "value": "BI"}, 
  {"viewvalue": "Cambodia", "value": "KH"}, 
  {"viewvalue": "Cameroon", "value": "CM"}, 
  {"viewvalue": "Canada", "value": "CA"}, 
  {"viewvalue": "Cape Verde", "value": "CV"}, 
  {"viewvalue": "Cayman Islands", "value": "KY"}, 
  {"viewvalue": "Central African Republic", "value": "CF"}, 
  {"viewvalue": "Chad", "value": "TD"}, 
  {"viewvalue": "Chile", "value": "CL"}, 
  {"viewvalue": "China", "value": "CN"}, 
  {"viewvalue": "Christmas Island", "value": "CX"}, 
  {"viewvalue": "Cocos (Keeling) Islands", "value": "CC"}, 
  {"viewvalue": "Colombia", "value": "CO"}, 
  {"viewvalue": "Comoros", "value": "KM"}, 
  {"viewvalue": "Congo", "value": "CG"}, 
  {"viewvalue": "Congo, The Democratic Republic of the", "value": "CD"}, 
  {"viewvalue": "Cook Islands", "value": "CK"}, 
  {"viewvalue": "Costa Rica", "value": "CR"}, 
  {"viewvalue": "Cote D\"Ivoire", "value": "CI"}, 
  {"viewvalue": "Croatia", "value": "HR"}, 
  {"viewvalue": "Cuba", "value": "CU"}, 
  {"viewvalue": "Cyprus", "value": "CY"}, 
  {"viewvalue": "Czech Republic", "value": "CZ"}, 
  {"viewvalue": "Denmark", "value": "DK"}, 
  {"viewvalue": "Djibouti", "value": "DJ"}, 
  {"viewvalue": "Dominica", "value": "DM"}, 
  {"viewvalue": "Dominican Republic", "value": "DO"}, 
  {"viewvalue": "Ecuador", "value": "EC"}, 
  {"viewvalue": "Egypt", "value": "EG"}, 
  {"viewvalue": "El Salvador", "value": "SV"}, 
  {"viewvalue": "Equatorial Guinea", "value": "GQ"}, 
  {"viewvalue": "Eritrea", "value": "ER"}, 
  {"viewvalue": "Estonia", "value": "EE"}, 
  {"viewvalue": "Ethiopia", "value": "ET"}, 
  {"viewvalue": "Falkland Islands (Malvinas)", "value": "FK"}, 
  {"viewvalue": "Faroe Islands", "value": "FO"}, 
  {"viewvalue": "Fiji", "value": "FJ"}, 
  {"viewvalue": "Finland", "value": "FI"}, 
  {"viewvalue": "France", "value": "FR"}, 
  {"viewvalue": "French Guiana", "value": "GF"}, 
  {"viewvalue": "French Polynesia", "value": "PF"}, 
  {"viewvalue": "French Southern Territories", "value": "TF"}, 
  {"viewvalue": "Gabon", "value": "GA"}, 
  {"viewvalue": "Gambia", "value": "GM"}, 
  {"viewvalue": "Georgia", "value": "GE"}, 
  {"viewvalue": "Germany", "value": "DE"}, 
  {"viewvalue": "Ghana", "value": "GH"}, 
  {"viewvalue": "Gibraltar", "value": "GI"}, 
  {"viewvalue": "Greece", "value": "GR"}, 
  {"viewvalue": "Greenland", "value": "GL"}, 
  {"viewvalue": "Grenada", "value": "GD"}, 
  {"viewvalue": "Guadeloupe", "value": "GP"}, 
  {"viewvalue": "Guam", "value": "GU"}, 
  {"viewvalue": "Guatemala", "value": "GT"}, 
  {"viewvalue": "Guernsey", "value": "GG"}, 
  {"viewvalue": "Guinea", "value": "GN"}, 
  {"viewvalue": "Guinea-Bissau", "value": "GW"}, 
  {"viewvalue": "Guyana", "value": "GY"}, 
  {"viewvalue": "Haiti", "value": "HT"}, 
  {"viewvalue": "Heard Island and Mcdonald Islands", "value": "HM"}, 
  {"viewvalue": "Holy See (Vatican City State)", "value": "VA"}, 
  {"viewvalue": "Honduras", "value": "HN"}, 
  {"viewvalue": "Hong Kong", "value": "HK"}, 
  {"viewvalue": "Hungary", "value": "HU"}, 
  {"viewvalue": "Iceland", "value": "IS"}, 
  {"viewvalue": "India", "value": "IN"}, 
  {"viewvalue": "Indonesia", "value": "ID"}, 
  {"viewvalue": "Iran, Islamic Republic Of", "value": "IR"}, 
  {"viewvalue": "Iraq", "value": "IQ"}, 
  {"viewvalue": "Ireland", "value": "IE"}, 
  {"viewvalue": "Isle of Man", "value": "IM"}, 
  {"viewvalue": "Israel", "value": "IL"}, 
  {"viewvalue": "Italy", "value": "IT"}, 
  {"viewvalue": "Jamaica", "value": "JM"}, 
  {"viewvalue": "Japan", "value": "JP"}, 
  {"viewvalue": "Jersey", "value": "JE"}, 
  {"viewvalue": "Jordan", "value": "JO"}, 
  {"viewvalue": "Kazakhstan", "value": "KZ"}, 
  {"viewvalue": "Kenya", "value": "KE"}, 
  {"viewvalue": "Kiribati", "value": "KI"}, 
  {"viewvalue": "Korea, Democratic People\"S Republic of", "value": "KP"}, 
  {"viewvalue": "Korea, Republic of", "value": "KR"}, 
  {"viewvalue": "Kuwait", "value": "KW"}, 
  {"viewvalue": "Kyrgyzstan", "value": "KG"}, 
  {"viewvalue": "Lao People\"S Democratic Republic", "value": "LA"}, 
  {"viewvalue": "Latvia", "value": "LV"}, 
  {"viewvalue": "Lebanon", "value": "LB"}, 
  {"viewvalue": "Lesotho", "value": "LS"}, 
  {"viewvalue": "Liberia", "value": "LR"}, 
  {"viewvalue": "Libyan Arab Jamahiriya", "value": "LY"}, 
  {"viewvalue": "Liechtenstein", "value": "LI"}, 
  {"viewvalue": "Lithuania", "value": "LT"}, 
  {"viewvalue": "Luxembourg", "value": "LU"}, 
  {"viewvalue": "Macao", "value": "MO"}, 
  {"viewvalue": "Macedonia, The Former Yugoslav Republic of", "value": "MK"}, 
  {"viewvalue": "Madagascar", "value": "MG"}, 
  {"viewvalue": "Malawi", "value": "MW"}, 
  {"viewvalue": "Malaysia", "value": "MY"}, 
  {"viewvalue": "Maldives", "value": "MV"}, 
  {"viewvalue": "Mali", "value": "ML"}, 
  {"viewvalue": "Malta", "value": "MT"}, 
  {"viewvalue": "Marshall Islands", "value": "MH"}, 
  {"viewvalue": "Martinique", "value": "MQ"}, 
  {"viewvalue": "Mauritania", "value": "MR"}, 
  {"viewvalue": "Mauritius", "value": "MU"}, 
  {"viewvalue": "Mayotte", "value": "YT"}, 
  {"viewvalue": "Mexico", "value": "MX"}, 
  {"viewvalue": "Micronesia, Federated States of", "value": "FM"}, 
  {"viewvalue": "Moldova, Republic of", "value": "MD"}, 
  {"viewvalue": "Monaco", "value": "MC"}, 
  {"viewvalue": "Mongolia", "value": "MN"}, 
  {"viewvalue": "Montserrat", "value": "MS"}, 
  {"viewvalue": "Morocco", "value": "MA"}, 
  {"viewvalue": "Mozambique", "value": "MZ"}, 
  {"viewvalue": "Myanmar", "value": "MM"}, 
  {"viewvalue": "Namibia", "value": "NA"}, 
  {"viewvalue": "Nauru", "value": "NR"}, 
  {"viewvalue": "Nepal", "value": "NP"}, 
  {"viewvalue": "Netherlands", "value": "NL"}, 
  {"viewvalue": "Netherlands Antilles", "value": "AN"}, 
  {"viewvalue": "New Caledonia", "value": "NC"}, 
  {"viewvalue": "New Zealand", "value": "NZ"}, 
  {"viewvalue": "Nicaragua", "value": "NI"}, 
  {"viewvalue": "Niger", "value": "NE"}, 
  {"viewvalue": "Nigeria", "value": "NG"}, 
  {"viewvalue": "Niue", "value": "NU"}, 
  {"viewvalue": "Norfolk Island", "value": "NF"}, 
  {"viewvalue": "Northern Mariana Islands", "value": "MP"}, 
  {"viewvalue": "Norway", "value": "NO"}, 
  {"viewvalue": "Oman", "value": "OM"}, 
  {"viewvalue": "Pakistan", "value": "PK"}, 
  {"viewvalue": "Palau", "value": "PW"}, 
  {"viewvalue": "Palestinian Territory, Occupied", "value": "PS"}, 
  {"viewvalue": "Panama", "value": "PA"}, 
  {"viewvalue": "Papua New Guinea", "value": "PG"}, 
  {"viewvalue": "Paraguay", "value": "PY"}, 
  {"viewvalue": "Peru", "value": "PE"}, 
  {"viewvalue": "Philippines", "value": "PH"}, 
  {"viewvalue": "Pitcairn", "value": "PN"}, 
  {"viewvalue": "Poland", "value": "PL"}, 
  {"viewvalue": "Portugal", "value": "PT"}, 
  {"viewvalue": "Puerto Rico", "value": "PR"}, 
  {"viewvalue": "Qatar", "value": "QA"}, 
  {"viewvalue": "Reunion", "value": "RE"}, 
  {"viewvalue": "Romania", "value": "RO"}, 
  {"viewvalue": "Russian Federation", "value": "RU"}, 
  {"viewvalue": "RWANDA", "value": "RW"}, 
  {"viewvalue": "Saint Helena", "value": "SH"}, 
  {"viewvalue": "Saint Kitts and Nevis", "value": "KN"}, 
  {"viewvalue": "Saint Lucia", "value": "LC"}, 
  {"viewvalue": "Saint Pierre and Miquelon", "value": "PM"}, 
  {"viewvalue": "Saint Vincent and the Grenadines", "value": "VC"}, 
  {"viewvalue": "Samoa", "value": "WS"}, 
  {"viewvalue": "San Marino", "value": "SM"}, 
  {"viewvalue": "Sao Tome and Principe", "value": "ST"}, 
  {"viewvalue": "Saudi Arabia", "value": "SA"}, 
  {"viewvalue": "Senegal", "value": "SN"}, 
  {"viewvalue": "Serbia and Montenegro", "value": "CS"}, 
  {"viewvalue": "Seychelles", "value": "SC"}, 
  {"viewvalue": "Sierra Leone", "value": "SL"}, 
  {"viewvalue": "Singapore", "value": "SG"}, 
  {"viewvalue": "Slovakia", "value": "SK"}, 
  {"viewvalue": "Slovenia", "value": "SI"}, 
  {"viewvalue": "Solomon Islands", "value": "SB"}, 
  {"viewvalue": "Somalia", "value": "SO"}, 
  {"viewvalue": "South Africa", "value": "ZA"}, 
  {"viewvalue": "South Georgia and the South Sandwich Islands", "value": "GS"}, 
  {"viewvalue": "Spain", "value": "ES"}, 
  {"viewvalue": "Sri Lanka", "value": "LK"}, 
  {"viewvalue": "Sudan", "value": "SD"}, 
  {"viewvalue": "Suriname", "value": "SR"}, 
  {"viewvalue": "Svalbard and Jan Mayen", "value": "SJ"}, 
  {"viewvalue": "Swaziland", "value": "SZ"}, 
  {"viewvalue": "Sweden", "value": "SE"}, 
  {"viewvalue": "Switzerland", "value": "CH"}, 
  {"viewvalue": "Syrian Arab Republic", "value": "SY"}, 
  {"viewvalue": "Taiwan, Province of China", "value": "TW"}, 
  {"viewvalue": "Tajikistan", "value": "TJ"}, 
  {"viewvalue": "Tanzania, United Republic of", "value": "TZ"}, 
  {"viewvalue": "Thailand", "value": "TH"}, 
  {"viewvalue": "Timor-Leste", "value": "TL"}, 
  {"viewvalue": "Togo", "value": "TG"}, 
  {"viewvalue": "Tokelau", "value": "TK"}, 
  {"viewvalue": "Tonga", "value": "TO"}, 
  {"viewvalue": "Trinidad and Tobago", "value": "TT"}, 
  {"viewvalue": "Tunisia", "value": "TN"}, 
  {"viewvalue": "Turkey", "value": "TR"}, 
  {"viewvalue": "Turkmenistan", "value": "TM"}, 
  {"viewvalue": "Turks and Caicos Islands", "value": "TC"}, 
  {"viewvalue": "Tuvalu", "value": "TV"}, 
  {"viewvalue": "Uganda", "value": "UG"}, 
  {"viewvalue": "Ukraine", "value": "UA"}, 
  {"viewvalue": "United Arab Emirates", "value": "AE"}, 
  {"viewvalue": "United Kingdom", "value": "GB"}, 
  {"viewvalue": "United States", "value": "US"}, 
  {"viewvalue": "United States Minor Outlying Islands", "value": "UM"}, 
  {"viewvalue": "Uruguay", "value": "UY"}, 
  {"viewvalue": "Uzbekistan", "value": "UZ"}, 
  {"viewvalue": "Vanuatu", "value": "VU"}, 
  {"viewvalue": "Venezuela", "value": "VE"}, 
  {"viewvalue": "Viet Nam", "value": "VN"}, 
  {"viewvalue": "Virgin Islands, British", "value": "VG"}, 
  {"viewvalue": "Virgin Islands, U.S.", "value": "VI"}, 
  {"viewvalue": "Wallis and Futuna", "value": "WF"}, 
  {"viewvalue": "Western Sahara", "value": "EH"}, 
  {"viewvalue": "Yemen", "value": "YE"}, 
  {"viewvalue": "Zambia", "value": "ZM"}, 
  {"viewvalue": "Zimbabwe", "value": "ZW"} 
]
 